xrd_rust-0.2.0.dist-info/METADATA
xrd_rust-0.2.0.dist-info/WHEEL
xrd_rust_calculator/__init__.py
xrd_rust_calculator/atomic_scattering_params.json
xrd_rust_calculator/xrd_calculator_rust.py
xrd_rust_calculator/xrd_rust_accelerator.cpython-39-darwin.so
xrd_rust-0.2.0.dist-info/RECORD
